epub_pinyin/__init__.py
epub_pinyin/epub_parser.py
epub_pinyin/main.py
epub_pinyin/pdf_converter.py
epub_pinyin/polyphonic_dict.py
epub_pinyin/text_processor.py
epub_pinyin/fonts/SimSun.ttc
epub_pinyin-0.2.1.dist-info/entry_points.txt
epub_pinyin-0.2.1.dist-info/licenses/LICENSE
epub_pinyin-0.2.1.dist-info/WHEEL
epub_pinyin-0.2.1.dist-info/METADATA
epub_pinyin-0.2.1.dist-info/RECORD
