Metadata-Version: 2.4
Name: epub-pinyin
Version: 0.2.1
Summary: Add Pinyin annotations to Chinese text in EPUB files with smart polyphonic character handling
Keywords: epub,pinyin,chinese,annotation,pdf,text-processing
Author-email: Tony <tony.develop.2025@gmail.com>
Maintainer-email: Tony <tony.develop.2025@gmail.com>
Requires-Python: >=3.7
Classifier: Development Status :: 4 - Beta
Classifier: Intended Audience :: End Users/Desktop
Classifier: Topic :: Text Processing :: Markup :: XML
Classifier: Programming Language :: Python :: 3
Classifier: Programming Language :: Python :: 3.7
Classifier: Programming Language :: Python :: 3.8
Classifier: Programming Language :: Python :: 3.9
Classifier: Programming Language :: Python :: 3.10
Classifier: Programming Language :: Python :: 3.11
Classifier: Programming Language :: Python :: 3.12
Classifier: Operating System :: OS Independent
Requires-Dist: beautifulsoup4>=4.12.0
Requires-Dist: pypinyin>=0.50.0
Requires-Dist: jieba>=0.42.1
Requires-Dist: lxml>=4.9.0
Requires-Dist: pytest>=8.0.0 ; extra == "dev"
Requires-Dist: reportlab>=4.0.0 ; extra == "dev"
Requires-Dist: twine>=4.0.0 ; extra == "dev"
Requires-Dist: build>=0.10.0 ; extra == "dev"
Requires-Dist: reportlab>=4.0.0 ; extra == "pdf"
Project-URL: Documentation, https://github.com/tony-develop-2025/epub-pinyin#readme
Project-URL: Homepage, https://github.com/tony-develop-2025/epub-pinyin
Project-URL: Issues, https://github.com/tony-develop-2025/epub-pinyin/issues
Project-URL: Repository, https://github.com/tony-develop-2025/epub-pinyin
Provides-Extra: dev
Provides-Extra: pdf
